<!--
    Theme capabilities for Aura-es-de
-->

<themeCapabilities>
   
   <themeName>Aura</themeName>

   <aspectRatio>16:9</aspectRatio>
   <aspectRatio>16:10</aspectRatio>
   <aspectRatio>4:3</aspectRatio>
   <aspectRatio>8:7</aspectRatio>
   <aspectRatio>1:1</aspectRatio>
   
   <aspectRatio>3:2</aspectRatio>
   <aspectRatio>19.5:9</aspectRatio>
   <aspectRatio>21:9</aspectRatio>


   <fontSize>small</fontSize>
   <fontSize>medium</fontSize>
   <fontSize>large</fontSize>
   <fontSize>x-large</fontSize>

   
   <colorScheme name="logo-purple">
      <label>[Logo] Purple</label>
   </colorScheme>  
   <colorScheme name="logo-blue">
      <label>[Logo] Blue</label>
   </colorScheme>
   <colorScheme name="logo-green">
      <label>[Logo] Green</label>
   </colorScheme>
   <colorScheme name="logo-orange">
      <label>[Logo] Orange</label>
   </colorScheme>
   <colorScheme name="logo-black">
      <label>[Logo] Black</label>
   </colorScheme>
   <colorScheme name="art-light-glass">
      <label>[Art] Light Glass</label>
   </colorScheme>  
   <colorScheme name="art-dark-glass">
      <label>[Art] Dark Glass</label>
   </colorScheme> 
   <colorScheme name="art-purple">
      <label>[Art] Purple</label>
   </colorScheme>  
   <colorScheme name="art-blue">
      <label>[Art] Blue</label>
   </colorScheme>
   <colorScheme name="art-green">
      <label>[Art] Green</label>
   </colorScheme>
   <colorScheme name="art-orange">
      <label>[Art] Orange</label>
   </colorScheme>  
   <colorScheme name="art-black">
      <label>[Art] Black</label>
   </colorScheme>

   <transitions name="transitions">
      <label>transitions</label>
      <selectable>false</selectable>
      <systemToSystem>instant</systemToSystem>
      <systemToGamelist>instant</systemToGamelist>
      <gamelistToGamelist>instant</gamelistToGamelist>
      <gamelistToSystem>instant</gamelistToSystem>
      <startupToSystem>instant</startupToSystem>
      <startupToGamelist>instant</startupToGamelist>
   </transitions>
   <suppressTransitionProfiles>
      <entry>builtin-instant</entry>
      <entry>builtin-slide</entry>
      <entry>builtin-fade</entry>
   </suppressTransitionProfiles>

   <variant name="carousel-textlist">
      <label>[Carousel] Textlist</label>
      <selectable>true</selectable>
   </variant>
   <variant name="carousel-detailed-grid">
      <label>[Carousel] Detailed-Grid</label>
      <selectable>true</selectable>
   </variant>
   <variant name="carousel-detailed-grid-help-off">
      <label>[Carousel] Detailed-Grid (Help Off)</label>
      <selectable>true</selectable>
   </variant>
   <variant name="carousel-basic-grid">
      <label>[Carousel] Basic-Grid</label>
      <selectable>true</selectable>
   </variant>
   <variant name="carousel-basic-grid-help-off">
      <label>[Carousel] Basic-Grid (Help Off)</label>
      <selectable>true</selectable>
   </variant>
   <variant name="carousel-carousel-marquee">
      <label>[Carousel] Carousel-Marquee</label>
      <selectable>true</selectable>
   </variant>
   <variant name="carousel-carousel-boxart">
      <label>[Carousel] Carousel-Boxart</label>
      <selectable>true</selectable>
   </variant>

   <variant name="fullscreen-textlist">
      <label>[Fullscreen] Textlist</label>
      <selectable>true</selectable>
   </variant>
   <variant name="fullscreen-detailed-grid">
      <label>[Fullscreen] Detailed-Grid</label>
      <selectable>true</selectable>
   </variant>
   <variant name="fullscreen-detailed-grid-help-off">
      <label>[Fullscreen] Detailed-Grid (Help Off)</label>
      <selectable>true</selectable>
   </variant>
   <variant name="fullscreen-basic-grid">
      <label>[Fullscreen] Basic-Grid</label>
      <selectable>true</selectable>
   </variant>
   <variant name="fullscreen-basic-grid-help-off">
      <label>[Fullscreen] Basic-Grid (Help Off)</label>
      <selectable>true</selectable>
   </variant>
   <variant name="fullscreen-carousel-marquee">
      <label>[Fullscreen] Carousel-Marquee</label>
      <selectable>true</selectable>
   </variant>
   <variant name="fullscreen-carousel-boxart">
      <label>[Fullscreen] Carousel-Boxart</label>
      <selectable>true</selectable>
   </variant>

   <variant name="grid-textlist">
      <label>[Grid] Textlist</label>
      <selectable>true</selectable>
   </variant>
   <variant name="grid-detailed-grid">
      <label>[Grid] Detailed-Grid</label>
      <selectable>true</selectable>
   </variant>
   <variant name="grid-detailed-grid-help-off">
      <label>[Grid] Detailed-Grid (Help Off)</label>
      <selectable>true</selectable>
   </variant>
   <variant name="grid-basic-grid">
      <label>[Grid] Basic-Grid</label>
      <selectable>true</selectable>
   </variant>
   <variant name="grid-basic-grid-help-off">
      <label>[Grid] Basic-Grid (Help Off)</label>
      <selectable>true</selectable>
   </variant>
   <variant name="grid-carousel-marquee">
      <label>[Grid] Carousel-Marquee</label>
      <selectable>true</selectable>
   </variant>
   <variant name="grid-carousel-boxart">
      <label>[Grid] Carousel-Boxart</label>
      <selectable>true</selectable>
   </variant>


</themeCapabilities>
