<theme>
           <aspectRatio name="1:1">           
                   <fontSize name="small">
                            <variables>
                               <!--   Detailed Grid Variables   -->          
                                        <item-w>0.134975</item-w>         
                                        <item-h>0.120269552529183</item-h>         
                            </variables>
                    </fontSize>
                   <fontSize name="medium">
                            <variables>
                               <!--   Detailed Grid Variables   -->          
                                        <item-w>0.179966666666667</item-w>         
                                        <item-h>0.160359403372244</item-h>         
                            </variables>
                    </fontSize>
                   <fontSize name="large">
                            <variables>
                               <!--   Detailed Grid Variables   -->          
                                        <item-w>0.26995</item-w>         
                                        <item-h>0.240539105058366</item-h>         
                            </variables>
                    </fontSize>
                   <fontSize name="x-large">
                            <variables>
                               <!--   Detailed Grid Variables   -->          
                                        <item-w>0.26995</item-w>         
                                        <item-h>0.240539105058366</item-h>         
                            </variables>
                    </fontSize>
             </aspectRatio>    
           <aspectRatio name="16:10">           
                   <fontSize name="small">
                            <variables>
                               <!--   Detailed Grid Variables   -->          
                                        <item-w>0.10798</item-w>         
                                        <item-h>0.153945027237354</item-h>         
                            </variables>
                    </fontSize>
                   <fontSize name="medium">
                            <variables>
                               <!--   Detailed Grid Variables   -->          
                                        <item-w>0.134975</item-w>         
                                        <item-h>0.192431284046693</item-h>         
                            </variables>
                    </fontSize>
                   <fontSize name="large">
                            <variables>
                               <!--   Detailed Grid Variables   -->          
                                        <item-w>0.179966666666667</item-w>         
                                        <item-h>0.25657504539559</item-h>         
                            </variables>
                    </fontSize>
                   <fontSize name="x-large">
                            <variables>
                               <!--   Detailed Grid Variables   -->          
                                        <item-w>0.179966666666667</item-w>         
                                        <item-h>0.25657504539559</item-h>         
                            </variables>
                    </fontSize>
             </aspectRatio>    
           <aspectRatio name="16:9">           
                   <fontSize name="small">
                            <variables>
                               <!--   Detailed Grid Variables   -->          
                                        <item-w>0.10798</item-w>         
                                        <item-h>0.171050030263727</item-h>         
                            </variables>
                    </fontSize>
                   <fontSize name="medium">
                            <variables>
                               <!--   Detailed Grid Variables   -->          
                                        <item-w>0.134975</item-w>         
                                        <item-h>0.213812537829658</item-h>         
                            </variables>
                    </fontSize>
                   <fontSize name="large">
                            <variables>
                               <!--   Detailed Grid Variables   -->          
                                        <item-w>0.179966666666667</item-w>         
                                        <item-h>0.285083383772878</item-h>         
                            </variables>
                    </fontSize>
                   <fontSize name="x-large">
                            <variables>
                               <!--   Detailed Grid Variables   -->          
                                        <item-w>0.179966666666667</item-w>         
                                        <item-h>0.285083383772878</item-h>         
                            </variables>
                    </fontSize>
             </aspectRatio>    
           <aspectRatio name="19.5:9">           
                   <fontSize name="small">
                            <variables>
                               <!--   Detailed Grid Variables   -->          
                                        <item-w>0.0899833333333333</item-w>         
                                        <item-h>0.173722686986598</item-h>         
                            </variables>
                    </fontSize>
                   <fontSize name="medium">
                            <variables>
                               <!--   Detailed Grid Variables   -->          
                                        <item-w>0.10798</item-w>         
                                        <item-h>0.208467224383917</item-h>         
                            </variables>
                    </fontSize>
                   <fontSize name="large">
                            <variables>
                               <!--   Detailed Grid Variables   -->          
                                        <item-w>0.134975</item-w>         
                                        <item-h>0.260584030479896</item-h>         
                            </variables>
                    </fontSize>
                   <fontSize name="x-large">
                            <variables>
                               <!--   Detailed Grid Variables   -->          
                                        <item-w>0.134975</item-w>         
                                        <item-h>0.260584030479896</item-h>         
                            </variables>
                    </fontSize>
             </aspectRatio>    
           <aspectRatio name="21:9">           
                   <fontSize name="small">
                            <variables>
                               <!--   Detailed Grid Variables   -->          
                                        <item-w>0.0899833333333333</item-w>         
                                        <item-h>0.187085970600951</item-h>         
                            </variables>
                    </fontSize>
                   <fontSize name="medium">
                            <variables>
                               <!--   Detailed Grid Variables   -->          
                                        <item-w>0.10798</item-w>         
                                        <item-h>0.224503164721141</item-h>         
                            </variables>
                    </fontSize>
                   <fontSize name="large">
                            <variables>
                               <!--   Detailed Grid Variables   -->          
                                        <item-w>0.134975</item-w>         
                                        <item-h>0.280628955901427</item-h>         
                            </variables>
                    </fontSize>
                   <fontSize name="x-large">
                            <variables>
                               <!--   Detailed Grid Variables   -->          
                                        <item-w>0.134975</item-w>         
                                        <item-h>0.280628955901427</item-h>         
                            </variables>
                    </fontSize>
             </aspectRatio>    
           <aspectRatio name="3:2">           
                   <fontSize name="small">
                            <variables>
                               <!--   Detailed Grid Variables   -->          
                                        <item-w>0.10798</item-w>         
                                        <item-h>0.144323463035019</item-h>         
                            </variables>
                    </fontSize>
                   <fontSize name="medium">
                            <variables>
                               <!--   Detailed Grid Variables   -->          
                                        <item-w>0.134975</item-w>         
                                        <item-h>0.180404328793774</item-h>         
                            </variables>
                    </fontSize>
                   <fontSize name="large">
                            <variables>
                               <!--   Detailed Grid Variables   -->          
                                        <item-w>0.179966666666667</item-w>         
                                        <item-h>0.240539105058366</item-h>         
                            </variables>
                    </fontSize>
                   <fontSize name="x-large">
                            <variables>
                               <!--   Detailed Grid Variables   -->          
                                        <item-w>0.179966666666667</item-w>         
                                        <item-h>0.240539105058366</item-h>         
                            </variables>
                    </fontSize>
             </aspectRatio>    
           <aspectRatio name="4:3">           
                   <fontSize name="small">
                            <variables>
                               <!--   Detailed Grid Variables   -->          
                                        <item-w>0.134975</item-w>         
                                        <item-h>0.160359403372244</item-h>         
                            </variables>
                    </fontSize>
                   <fontSize name="medium">
                            <variables>
                               <!--   Detailed Grid Variables   -->          
                                        <item-w>0.179966666666667</item-w>         
                                        <item-h>0.213812537829658</item-h>         
                            </variables>
                    </fontSize>
                   <fontSize name="large">
                            <variables>
                               <!--   Detailed Grid Variables   -->          
                                        <item-w>0.26995</item-w>         
                                        <item-h>0.320718806744488</item-h>         
                            </variables>
                    </fontSize>
                   <fontSize name="x-large">
                            <variables>
                               <!--   Detailed Grid Variables   -->          
                                        <item-w>0.26995</item-w>         
                                        <item-h>0.320718806744488</item-h>         
                            </variables>
                    </fontSize>
             </aspectRatio>    
</theme>

